{
    "notifications": [
        {
            "id": "1",
            "title": "Уведомление 1",
            "description": "Уведомление 1 пришло",
            "userId": "1"
        },
        {
            "id": "2",
            "title": "Уведомление 2",
            "description": "Уведомление 2 пришло",
            "userId": "1",
            "href": "http://localhost:3000/admin"
        },
        {
            "id": "3",
            "title": "Уведомление 3",
            "description": "Уведомление 3 пришло",
            "userId": "2",
            "href": "http://localhost:3000/articles"
        },
        {
            "id": "4",
            "title": "Уведомление 4",
            "description": "Уведомление 4 пришло",
            "userId": "1"
        },
        {
            "id": "5",
            "title": "Уведомление 5",
            "description": "Уведомление 5 пришло",
            "userId": "2"
        }
    ],
    "articles": [
        {
            "id": "1",
            "title": "Создатель Node.js попросил Oracle сделать общедоступным товарный знак JavaScript",
            "subtitle": "Создатель Node.js и автор Deno Райан Даль в открытом письме попросил компанию Oracle сделать общедоступным товарный знак JavaScript.",
            "img": "https://hsto.org/webt/ue/ow/aa/ueowaarrj6vklb9kvxh2-kh-xeq.png",
            "views": 4302,
            "createdAt": "06.09.2022",
            "userId": "2",
            "type": ["IT"],
            "blocks": [
                {
                    "id": "1",
                    "type": "TEXT",
                    "paragraphs": [
                        "Создатель Node.js и автор Deno Райан Даль в открытом письме попросил компанию Oracle сделать общедоступным товарный знак JavaScript.",
                        "Даль напомнил, что в 1995 году Netscape заключила партнёрское соглашение с Sun Microsystems для создания интерактивных веб-сайтов. Разработчик Брендан Айк за 10 дней без сна создал первую версию JavaScript — динамического языка программирования, который только примерно синтаксически восходит к языку Java компании Sun. В результате этого партнёрства Sun получила торговую марку JavaScript. В 2009 году Oracle приобрела Sun Microsystems, и ей досталась в итоге торговая марка на JavaScript.",
                        "Айк этому поводу ранее пояснил, что JavaScript не столько связан с Java, сколько с общим предком C в синтаксисе. Он сделал именно язык программирования для HTML, для использования веб-дизайнерами и программистами, встроенный непосредственно в веб-страницу, в отличие от профессионального языка Java, где нужно запускать реальный код с объявлениями типов и использовать мощный компилятор. Айк назвал первые 10 дней создания JavaScript «срочной работой, выполняя которую, он знал, что там будут ошибки и пробелы». Поэтому он создал этот язык очень гибким, что в итоге позволило веб-разработчикам сделать его таким, каким они хотят его видеть.",
                        "Даль пояснил, что сам по себе товарный знак на JavaScript не имеет коммерческой ценности, так как кроме Oracle JavaScript Extension Toolkit у Oracle нет продуктов, использующих этот товарный знак, и, предположительно, не запланировано их использование. По его словам, Oracle не участвует в разработке каких-либо версий движков JavaScript, например, V8, JavaScriptCore или Spidermonkey. Даль предполагает, что, весьма вероятно, нарушение прав на товарный знак JavaScript не будет иметь исковой силы в суде из-за несоблюдения правил его неиспользования со стороны Oracle, но компании нужно показать это самой и сделать открытым для сообщества.",
                        "«Тем не менее, торговая марка — это тёмная туча, нависшая над самым популярным в мире языком программирования. Осторожные и законопослушные разработчики из кожи вон лезут, чтобы избежать его использования, что приводит к запутанным терминам, таким как ECMAScript», — уточнил Даль.",
                        "Ссылка на референс: https://habr.com/ru/news/686650/"
                    ]
                }
            ]
        },
        {
            "id": "2",
            "title": "Курс «Python для инженеров». Старт 3 потока 31 января",
            "subtitle": "Курс нацелен дать максимальную пользу, поэтому в нём нет абстрактных задач и любых проявлений Python для веба, аналитики и бекенда.",
            "img": "https://hsto.org/getpro/habr/upload_files/fd6/38c/9d5/fd638c9d532ccde21681605c8f7a8f77.png",
            "views": 8598,
            "createdAt": "20.01.2022",
            "userId": "4",
            "type": ["IT"],
            "blocks": [
                {
                    "id": "1",
                    "type": "TEXT",
                    "paragraphs": [
                        "Курс нацелен дать максимальную пользу, поэтому в нём нет абстрактных задач и любых проявлений Python для веба, аналитики и бекенда.",
                        "Будет разбор библиотек Python для DevOps, правила эффективного и поддерживаемого кода, решение конкретных задач DevOps.",
                        "Обучение закрепим проектом. Мы предлагаем тему на выбор, но рекомендуем взять свою рабочую задачу."
                    ]
                },
                {
                    "id": "2",
                    "type": "TEXT",
                    "title": "Примеры, что можно автоматизировать с Python:",
                    "paragraphs": [
                        "Автоматизация создания задач об инцидентах в таск-трекере",
                        "Инструмент для анализа и отключения холостых ресурсов",
                        "Автоматизация изменения конфигурации сервера",
                        "Ссылка на референс: https://habr.com/ru/companies/southbridge/news/646825/"
                    ]
                }
            ]
        },
        {
            "id": "3",
            "title": "Корни RxJava — о чем мы не подозревали",
            "subtitle": "",
            "img": "https://hsto.org/getpro/habr/upload_files/d22/944/840/d22944840b95951898047a949b53a2de.png",
            "views": 3687,
            "createdAt": "09.04.2023",
            "userId": "2",
            "type": ["IT"],
            "blocks": [
                {
                    "id": "1",
                    "type": "TEXT",
                    "paragraphs": [
                        "Всем привет, меня зовут Руслан, я Head of mobile development в одной международной компании. В нашей производственной практике достаточно много проектов используют для упрощенной работы с асинхронщиной фреймворк RxJava.",
                        "Обычно изучение RxJava в большинстве статей или онлайн-школ начинается со слов «Жил был Observable/Single/Flowable и мы решили на него подписаться».",
                        "После всего этого, как правило идёт пару слов про операторы, усиленный разбор отличий map от flatMap, concatMap, switchMap (мне сразу вспоминается среднестатистическое собеседование в какой-нибудь компании). Дальше идет что-то не очень внятное и совсем теоретическое про горячие источники и на этом всё.",
                        "Ссылка на референс: https://habr.com/ru/articles/727892/"
                    ]
                }
            ]
        },
        {
            "id": "4",
            "title": "Разработчики предложили убрать логотип Google с главной страницы Golang",
            "subtitle": "Что нового в JS за 2022 год?",
            "img": "https://teknotower.com/wp-content/uploads/2020/11/js.png",
            "views": 11653,
            "createdAt": "26.02.2022",
            "userId": "1",
            "type": ["IT"],
            "blocks": [
                {
                    "id": "1",
                    "type": "TEXT",
                    "title": "Заголовок этого блока",
                    "paragraphs": [
                        "Официальный аккаунт языка программирования Go в твиттере опубликовал пост с просьбой дать отзыв о новом облике своего веб-сайта. В комментариях один из пользователей заявил, что было ошибкой добавлять логотип Google в нижнем правом углу главной страницы. «Многие люди связывают проект с коммерческим продуктом Google».",
                        "Предложение вынесли на обсуждение в GitHub. Решение озвучил Эндрю Бонвентра, ведущий инженер в Go Team.",
                        "«Мы потратили много времени на то, чтобы обсудить это. Важно прояснить, что Google поддерживает Go. Google оплачивает хостинг и инфраструктуру, на которой работает golang.org, и мы надеемся, что нынешний маленький логотип — достойный компромисс», — написал он и закрыл вопрос.",
                        "Разработчик Тим Шойерманн, создавший обсуждение, ответил: «Я благодарен Google за финансирование первоначальной и текущей разработки Go, но Google не единственная компания, инвестирующая [в] Go. Я хотел бы перенести логотип Google в отдельный раздел вместе с основными заинтересованными сторонами проекта».",
                        "В следующем комментарии он добавил: «Я ценю участие Google в Go. Но наличие логотипа Google в углу каждой страницы golang.org позволяет предположить, что это чистый проект Google, хотя это не так».\nТем не менее, логотип компании пока остался на месте.",
                        "Ссылка на референс: https://habr.com/ru/news/460333/"
                    ]
                }
            ]
        },
        {
            "id": "5",
            "title": "Javascript news 5",
            "subtitle": "Что нового в JS за 2022 год?",
            "img": "https://teknotower.com/wp-content/uploads/2020/11/js.png",
            "views": 54321,
            "createdAt": "26.02.2022",
            "userId": "1",
            "type": ["IT"],
            "blocks": [
                {
                    "id": "1",
                    "type": "TEXT",
                    "title": "Заголовок этого блока",
                    "paragraphs": [
                        "Программа, которую по традиции называют «Hello, world!», очень проста. Она выводит куда-либо фразу «Hello, world!», или другую подобную, средствами некоего языка.",
                        "JavaScript — это язык, программы на котором можно выполнять в разных средах. В нашем случае речь идёт о браузерах и о серверной платформе Node.js. Если до сих пор вы не написали ни строчки кода на JS и читаете этот текст в браузере, на настольном компьютере, это значит, что вы буквально в считанных секундах от своей первой JavaScript-программы.",
                        "Существуют и другие способы запуска JS-кода в браузере. Так, если говорить об обычном использовании программ на JavaScript, они загружаются в браузер для обеспечения работы веб-страниц. Как правило, код оформляют в виде отдельных файлов с расширением .js, которые подключают к веб-страницам, но программный код можно включать и непосредственно в код страницы. Всё это делается с помощью тега <script>. Когда браузер обнаруживает такой код, он выполняет его. Подробности о теге script можно посмотреть на сайте w3school.com. В частности, рассмотрим пример, демонстрирующий работу с веб-страницей средствами JavaScript, приведённый на этом ресурсе. Этот пример можно запустить и средствами данного ресурса (ищите кнопку Try it Yourself), но мы поступим немного иначе. А именно, создадим в каком-нибудь текстовом редакторе (например — в VS Code или в Notepad++) новый файл, который назовём hello.html, и добавим в него следующий код:"
                    ]
                }
            ]
        },
        {
            "id": "6",
            "title": "Javascript news 6",
            "subtitle": "Что нового в JS за 2022 год?",
            "img": "https://teknotower.com/wp-content/uploads/2020/11/js.png",
            "views": 1022322,
            "createdAt": "26.02.2022",
            "userId": "1",
            "type": ["IT"],
            "blocks": [
                {
                    "id": "1",
                    "type": "TEXT",
                    "title": "Заголовок этого блока",
                    "paragraphs": [
                        "Программа, которую по традиции называют «Hello, world!», очень проста. Она выводит куда-либо фразу «Hello, world!», или другую подобную, средствами некоего языка.",
                        "JavaScript — это язык, программы на котором можно выполнять в разных средах. В нашем случае речь идёт о браузерах и о серверной платформе Node.js. Если до сих пор вы не написали ни строчки кода на JS и читаете этот текст в браузере, на настольном компьютере, это значит, что вы буквально в считанных секундах от своей первой JavaScript-программы.",
                        "Существуют и другие способы запуска JS-кода в браузере. Так, если говорить об обычном использовании программ на JavaScript, они загружаются в браузер для обеспечения работы веб-страниц. Как правило, код оформляют в виде отдельных файлов с расширением .js, которые подключают к веб-страницам, но программный код можно включать и непосредственно в код страницы. Всё это делается с помощью тега <script>. Когда браузер обнаруживает такой код, он выполняет его. Подробности о теге script можно посмотреть на сайте w3school.com. В частности, рассмотрим пример, демонстрирующий работу с веб-страницей средствами JavaScript, приведённый на этом ресурсе. Этот пример можно запустить и средствами данного ресурса (ищите кнопку Try it Yourself), но мы поступим немного иначе. А именно, создадим в каком-нибудь текстовом редакторе (например — в VS Code или в Notepad++) новый файл, который назовём hello.html, и добавим в него следующий код:"
                    ]
                }
            ]
        },
        {
            "id": "7",
            "title": "Javascript news 7",
            "subtitle": "Что нового в JS за 2022 год?",
            "img": "https://teknotower.com/wp-content/uploads/2020/11/js.png",
            "views": 102542,
            "createdAt": "26.02.2022",
            "userId": "1",
            "type": ["IT"],
            "blocks": [
                {
                    "id": "1",
                    "type": "TEXT",
                    "title": "Заголовок этого блока",
                    "paragraphs": [
                        "Программа, которую по традиции называют «Hello, world!», очень проста. Она выводит куда-либо фразу «Hello, world!», или другую подобную, средствами некоего языка.",
                        "JavaScript — это язык, программы на котором можно выполнять в разных средах. В нашем случае речь идёт о браузерах и о серверной платформе Node.js. Если до сих пор вы не написали ни строчки кода на JS и читаете этот текст в браузере, на настольном компьютере, это значит, что вы буквально в считанных секундах от своей первой JavaScript-программы.",
                        "Существуют и другие способы запуска JS-кода в браузере. Так, если говорить об обычном использовании программ на JavaScript, они загружаются в браузер для обеспечения работы веб-страниц. Как правило, код оформляют в виде отдельных файлов с расширением .js, которые подключают к веб-страницам, но программный код можно включать и непосредственно в код страницы. Всё это делается с помощью тега <script>. Когда браузер обнаруживает такой код, он выполняет его. Подробности о теге script можно посмотреть на сайте w3school.com. В частности, рассмотрим пример, демонстрирующий работу с веб-страницей средствами JavaScript, приведённый на этом ресурсе. Этот пример можно запустить и средствами данного ресурса (ищите кнопку Try it Yourself), но мы поступим немного иначе. А именно, создадим в каком-нибудь текстовом редакторе (например — в VS Code или в Notepad++) новый файл, который назовём hello.html, и добавим в него следующий код:"
                    ]
                }
            ]
        }
    ],
    "comments": [
        {
            "id": "1",
            "text": "some comment",
            "articleId": "1",
            "userId": "1"
        },
        {
            "id": "2",
            "text": "some comment 2",
            "articleId": "1",
            "userId": "2"
        },
        {
            "id": "3",
            "text": "some comment 3",
            "articleId": "1",
            "userId": "1"
        }
    ],
    "users": [
        {
            "id": "1",
            "username": "admin",
            "password": "123",
            "roles": ["ADMIN"],
            "avatar": "https://icon-library.com/images/avatar-icon-images/avatar-iconimages-4.jpg"
        },
        {
            "id": "2",
            "username": "machumak00",
            "password": "123",
            "roles": ["USER"],
            "avatar": "https://m.economictimes.com/thumb/msid-98683708,width-1200,height-900,resizemode-4,imgsize-99158/russian-hacktivist-group-phoenix-targets-indias-health-ministry-website-cloudsek.jpg"
        },
        {
            "id": "3",
            "username": "manager",
            "password": "123",
            "roles": ["MANAGER"],
            "avatar": "https://cdn-icons-png.flaticon.com/512/76/76828.png"
        },
        {
            "id": "4",
            "username": "test_user",
            "password": "123",
            "roles": ["USER"],
            "avatar": "https://cdn-icons-png.flaticon.com/512/76/76828.png"
        }
    ],
    "profile": [
        {
            "id": "1",
            "firstname": "Админ",
            "lastname": "Админов",
            "age": 23,
            "currency": "RUB",
            "country": "Russia",
            "city": "Perm",
            "username": "admin",
            "avatar": "https://icon-library.com/images/avatar-icon-images/avatar-icon-images-4.jpg"
        },
        {
            "id": "2",
            "firstname": "Михаил",
            "lastname": "Чумак",
            "age": 23,
            "currency": "RUB",
            "country": "Russia",
            "city": "Perm",
            "username": "machumak00",
            "avatar": "https://m.economictimes.com/thumb/msid-98683708,width-1200,height-900,resizemode-4,imgsize-99158/russian-hacktivist-group-phoenix-targets-indias-health-ministry-website-cloudsek.jpg"
        },
        {
            "id": "4",
            "firstname": "test",
            "lastname": "user",
            "age": 55,
            "currency": "RUB",
            "country": "Russia",
            "city": "Perm",
            "username": "test_user",
            "avatar": "https://m.economictimes.com/thumb/msid-98683708,width-1200,height-900,resizemode-4,imgsize-99158/russian-hacktivist-group-phoenix-targets-indias-health-ministry-website-cloudsek.jpg"
        }
    ],
    "article-ratings": [
        {
            "id": "1",
            "rate": 4,
            "feedback": "Хорошая статья",
            "userId": "1",
            "articleId": "1"
        },
        {
            "id": "2",
            "rate": 3,
            "feedback": "Такое",
            "userId": "1",
            "articleId": "2"
        },
        {
            "id": "4",
            "userId": "1",
            "articleId": "3",
            "rate": 4,
            "feedback": "Cool"
        },
        {
            "id": "3",
            "userId": "1",
            "articleId": "4",
            "rate": 1,
            "feedback": "Ужас"
        }
    ],
    "profile-ratings": [
        {
            "userId": "1",
            "profileId": "2",
            "rate": 4,
            "feedback": "Ок",
            "id": 1
        }
    ]
}
